GWDALI/GWDALI.py
GWDALI/__init__.py
GWDALI/Detectors_Sensitivity/Sn_CE.txt
GWDALI/Detectors_Sensitivity/Sn_ET.txt
GWDALI/Detectors_Sensitivity/Sn_K.txt
GWDALI/Detectors_Sensitivity/Sn_L.txt
GWDALI/Detectors_Sensitivity/Sn_V.txt
GWDALI/Detectors_Sensitivity/__init__.py
GWDALI/Detectors_Sensitivity/plot_Sn.py
GWDALI/lib/Angles_lib.py
GWDALI/lib/Auxiliar.py
GWDALI/lib/Corner_Plots.py
GWDALI/lib/Dictionaries.py
GWDALI/lib/Diff_Signal_Tensors.py
GWDALI/lib/Get_Tensors.py
GWDALI/lib/Likelihood.py
GWDALI/lib/Waveforms.py
GWDALI/lib/__init__.py
gwdali-0.1.4.dist-info/LICENSE
gwdali-0.1.4.dist-info/METADATA
gwdali-0.1.4.dist-info/WHEEL
gwdali-0.1.4.dist-info/top_level.txt
gwdali-0.1.4.dist-info/RECORD
