Metadata-Version: 2.1
Name: gwdali
Version: 0.1.4
Summary: A Fisher-Based Software for Parameter Estimation from Gravitational Waves
Author: Josiel Mendonça Soares de Souza
Author-email: josiel.jms7@gmail.com
License: BSD 3-Clause License
Keywords: fisher matrix,gravitational waves,gw,dali
License-File: LICENSE
